Metadata-Version: 2.1
Name: flightcontrol
Version: 0.2.0
Summary: Flight tracking resources
Home-page: https://github.com/TimHanewich/FlightControl
Author: Tim Hanewich
Author-email: tahanewich@live.com
License: MIT
Platform: UNKNOWN
